LICENSE
vzenith/__init__.py
vzenith/client.py
vzenith/event.py
vzenith/packet.py
vzenith_client-1.2.0.dist-info/LICENSE
vzenith_client-1.2.0.dist-info/METADATA
vzenith_client-1.2.0.dist-info/WHEEL
vzenith_client-1.2.0.dist-info/RECORD
