Metadata-Version: 2.1
Name: vzenith-client
Version: 1.2.0
Summary: A VisionZenith Intelligent Video System Client SDK in TCP protocol for Python.
Home-page: https://github.com/he-yaowen/vzenith-client
License: BSD-3-Clause
Keywords: license-plate-recognition,intelligent-video-system,vision-zenith
Author: HE Yaowen
Author-email: he.yaowen@hotmail.com
Requires-Python: >=3.9,<3.12
Classifier: Development Status :: 2 - Pre-Alpha
Classifier: Intended Audience :: Developers
Classifier: License :: OSI Approved :: BSD License
Classifier: Operating System :: OS Independent
Classifier: Programming Language :: Python :: 3
Classifier: Programming Language :: Python :: 3.9
Classifier: Programming Language :: Python :: 3.10
Classifier: Programming Language :: Python :: 3.11
Classifier: Topic :: Software Development :: Libraries :: Python Modules
Classifier: Topic :: System :: Monitoring
Project-URL: Repository, https://github.com/he-yaowen/vzenith-client.git
